README.rst
setup.py
coclust/__init__.py
coclust/coclust.py
coclust/initialization.py
coclust.egg-info/PKG-INFO
coclust.egg-info/SOURCES.txt
coclust.egg-info/dependency_links.txt
coclust.egg-info/entry_points.txt
coclust.egg-info/not-zip-safe
coclust.egg-info/requires.txt
coclust.egg-info/top_level.txt
coclust/clustering/__init__.py
coclust/clustering/spherical_kmeans.py
coclust/coclustering/__init__.py
coclust/coclustering/base_diagonal_coclust.py
coclust/coclustering/base_non_diagonal_coclust.py
coclust/coclustering/coclust_info.py
coclust/coclustering/coclust_mod.py
coclust/coclustering/coclust_spec_mod.py
coclust/evaluation/__init__.py
coclust/evaluation/external.py
coclust/evaluation/internal.py
coclust/io/__init__.py
coclust/io/data_loading.py
coclust/io/data_transformation.py
coclust/io/input_checking.py
coclust/io/notebook.py
coclust/visualization/__init__.py