Metadata-Version: 1.1
Name: coclust
Version: 0.2.0
Summary: coclustering algorithms for data mining
Home-page: UNKNOWN
Author: Francois Role, Stanislas Morbieu, Mohamed Nadif
Author-email: francois.role@gmail.com
License: BSD3
Platform: UNKNOWN
Classifier: Topic :: Scientific/Engineering :: Information Analysis
